tryharder/__init__.py
tryharder-0.0.1.dist-info/LICENSE
tryharder-0.0.1.dist-info/WHEEL
tryharder-0.0.1.dist-info/METADATA
tryharder-0.0.1.dist-info/RECORD
