Metadata-Version: 2.1
Name: tryharder
Version: 0.0.1
Summary: tryharder - A Python library for when Python just doesn't try hard enough 
Author-email: Christoph Kattmann <christoph.kattmann@gmail.com>
Classifier: License :: OSI Approved :: MIT License
Project-URL: Home, https://github.com/ckattmann/tryharder
